burrow.py
setup.cfg
setup.py
burrow.egg-info/PKG-INFO
burrow.egg-info/SOURCES.txt
burrow.egg-info/dependency_links.txt
burrow.egg-info/entry_points.txt
burrow.egg-info/requires.txt
burrow.egg-info/top_level.txt