Metadata-Version: 1.1
Name: burrow
Version: 0.0.4
Summary: Python Client For Nest Mobile API
Home-page: https://github.com/ramielrowe/burrow
Author: Andrew Melton
Author-email: ramielrowe@gmail.com
License: Apache
Keywords: nest thermostat
Platform: UNKNOWN
Classifier: Development Status :: 3 - Alpha
Classifier: Topic :: Utilities
